topsis/__init__.py
topsis/topsis.py
Topsis_Prisha_102116052-0.0.1.dist-info/LICENSE.txt
Topsis_Prisha_102116052-0.0.1.dist-info/METADATA
Topsis_Prisha_102116052-0.0.1.dist-info/WHEEL
Topsis_Prisha_102116052-0.0.1.dist-info/top_level.txt
Topsis_Prisha_102116052-0.0.1.dist-info/RECORD
