Metadata-Version: 2.1
Name: Topsis-Prisha-102116052
Version: 0.0.1
Summary: TOPSIS Application
Home-page: UNKNOWN
Author: Prisha Sawhney
Author-email: psawhney_be21@thapar.edu
License: UNKNOWN
Keywords: python,topsis
Platform: UNKNOWN
Classifier: Development Status :: 1 - Planning
Classifier: Intended Audience :: Developers
Classifier: Programming Language :: Python :: 3
Classifier: Operating System :: Unix
Classifier: Operating System :: MacOS :: MacOS X
Classifier: Operating System :: Microsoft :: Windows
License-File: LICENSE.txt
Requires-Dist: sys
Requires-Dist: os
Requires-Dist: pandas
Requires-Dist: numpy
